pynbaapi/__init__.py
pynbaapi/__version__.py
pynbaapi/constants.py
pynbaapi/nba.py
pynbaapi/api/__init__.py
pynbaapi/api/api.py
pynbaapi/api/endpoints/__init__.py
pynbaapi/api/endpoints/base.py
pynbaapi/api/endpoints/commonallplayers.py
pynbaapi/api/endpoints/commonteamroster.py
pynbaapi/api/endpoints/leaguestandings.py
pynbaapi/api/endpoints/scoreboardv2.py
pynbaapi/api/endpoints/teamdetails.py
pynbaapi/api/endpoints/teaminfocommon.py
pynbaapi/api/models/__init__.py
pynbaapi/api/models/base.py
pynbaapi-0.0.1.dist-info/LICENSE
pynbaapi-0.0.1.dist-info/METADATA
pynbaapi-0.0.1.dist-info/WHEEL
pynbaapi-0.0.1.dist-info/top_level.txt
pynbaapi-0.0.1.dist-info/RECORD
