Metadata-Version: 2.1
Name: pynbaapi
Version: 0.0.1
Summary: NBA API Wrapper for Python
Home-page: https://github.com/toddrob99/pynbaapi
Author: Todd Roberts
Author-email: todd@toddrob.com
License: UNKNOWN
Platform: UNKNOWN
Classifier: Development Status :: 4 - Beta
Classifier: Programming Language :: Python
Classifier: Programming Language :: Python :: 3
Classifier: Programming Language :: Python :: 3.8
Classifier: License :: OSI Approved :: MIT License
Classifier: Operating System :: OS Independent
License-File: LICENSE
Requires-Dist: requests
